MANIFEST.in
README.rst
setup.py
collective/__init__.py
collective.datagridcolumns.egg-info/PKG-INFO
collective.datagridcolumns.egg-info/SOURCES.txt
collective.datagridcolumns.egg-info/dependency_links.txt
collective.datagridcolumns.egg-info/entry_points.txt
collective.datagridcolumns.egg-info/namespace_packages.txt
collective.datagridcolumns.egg-info/not-zip-safe
collective.datagridcolumns.egg-info/requires.txt
collective.datagridcolumns.egg-info/top_level.txt
collective/datagridcolumns/DateColumn.py
collective/datagridcolumns/MultiSelectColumn.py
collective/datagridcolumns/ReferenceColumn.py
collective/datagridcolumns/SelectColumn.py
collective/datagridcolumns/TextAreaColumn.py
collective/datagridcolumns/__init__.py
collective/datagridcolumns/calling_content_provider.py
collective/datagridcolumns/configure.zcml
collective/datagridcolumns/interfaces.py
collective/datagridcolumns/tests.py
collective/datagridcolumns/Extensions/install.py
collective/datagridcolumns/browser/__init__.py
collective/datagridcolumns/browser/autocomplete.py
collective/datagridcolumns/browser/configure.zcml
collective/datagridcolumns/browser/jquery-1.4.4.min.js
collective/datagridcolumns/profiles/default/metadata.xml
collective/datagridcolumns/profiles/default/skins.xml
collective/datagridcolumns/profiles/jquery/jsregistry.xml
collective/datagridcolumns/profiles/uninstall/skins.xml
collective/datagridcolumns/skins/collective.datagridcolumns/datagrid_date_cell.pt
collective/datagridcolumns/skins/collective.datagridcolumns/datagrid_multiselect_cell.pt
collective/datagridcolumns/skins/collective.datagridcolumns/datagrid_reference_cell.pt
collective/datagridcolumns/skins/collective.datagridcolumns/datagrid_textarea_cell.pt
collective/datagridcolumns/skins/collective.datagridcolumns/datagridautocomplete.js
collective/datagridcolumns/skins/collective.datagridcolumns/datagriddatepicker.js
collective/datagridcolumns/skins/collective.datagridcolumns/datagridmultiselect.js
collective/datagridcolumns/skins/collective.datagridcolumns/datagridwidget_patches.js
docs/HISTORY.rst
docs/INSTALL.txt
docs/LICENSE.GPL
docs/LICENSE.txt