Metadata-Version: 1.0
Name: collective.datagridcolumns
Version: 0.7.0
Summary: Additional columns for Plone and DataGridField
Home-page: http://plone.org/products/collective.datagridcolumns
Author: RedTurtle Technology
Author-email: sviluppoplone@redturtle.it
License: GPL
Keywords: plonegov plone datagridfield archetypes jqueryui widget
Platform: UNKNOWN
Classifier: Framework :: Plone
Classifier: Framework :: Plone :: 3.3
Classifier: Framework :: Plone :: 4.0
Classifier: Framework :: Plone :: 4.1
Classifier: Framework :: Plone :: 4.2
Classifier: Framework :: Plone :: 4.3
Classifier: Development Status :: 5 - Production/Stable
Classifier: Programming Language :: Python
